sphinxcontrib/video/__init__.py
sphinxcontrib_video-0.4.0.dist-info/LICENSE
sphinxcontrib_video-0.4.0.dist-info/METADATA
sphinxcontrib_video-0.4.0.dist-info/WHEEL
sphinxcontrib_video-0.4.0.dist-info/top_level.txt
sphinxcontrib_video-0.4.0.dist-info/RECORD
