Metadata-Version: 2.2
Name: sphinxcontrib-video
Version: 0.4.0
Summary: Allows embedding of HTML5 videos in sphinx
Author-email: Raphael Massabot <rmassabot@gmail.com>
License: Apache Software License
Project-URL: repository, https://github.com/sphinx-contrib/video
Classifier: Development Status :: 3 - Alpha
Classifier: Framework :: Sphinx :: Extension
Classifier: Intended Audience :: Developers
Classifier: License :: OSI Approved :: Apache Software License
Classifier: Operating System :: OS Independent
Classifier: Programming Language :: Python
Classifier: Programming Language :: Python :: 3
Classifier: Programming Language :: Python :: 3.6
Classifier: Programming Language :: Python :: 3.7
Classifier: Programming Language :: Python :: 3.8
Classifier: Programming Language :: Python :: 3.9
Classifier: Programming Language :: Python :: 3.10
Classifier: Programming Language :: Python :: 3.11
Classifier: Programming Language :: Python :: 3.12
Classifier: Programming Language :: Python :: 3.13
Classifier: Topic :: Documentation
Classifier: Topic :: Utilities
Requires-Python: >=3.6.9
License-File: LICENSE
Requires-Dist: sphinx
Provides-Extra: dev
Requires-Dist: nox; extra == "dev"
Requires-Dist: pre-commit; extra == "dev"
Requires-Dist: mypy; extra == "dev"
Provides-Extra: test
Requires-Dist: pytest; extra == "test"
Requires-Dist: beautifulsoup4; extra == "test"
Requires-Dist: pytest-regressions; extra == "test"
Requires-Dist: pytest-cov; extra == "test"
Requires-Dist: defusedxml; extra == "test"
Provides-Extra: doc
Requires-Dist: pydata-sphinx-theme; extra == "doc"
Requires-Dist: sphinx-design; extra == "doc"
